{
	"ele": "544",
	"tpabr": "uf",
	"cdabr": "RR",
	"carper": "1",
	"md": "S",
	"t": "1",
	"f": "o",
	"dg": "04/10/2022",
	"hg": "12:07:14",
	"dt": "02/10/2022",
	"ht": "20:07:58",
	"dv": "s",
	"tf": "s",
	"v": "1",
	"esae": "n",
	"mnae": "",
	"s": "1268",
	"st": "1268",
	"pst": "100,00",
	"snt": "0",
	"psnt": "0,00",
	"si": "1268",
	"psi": "100,00",
	"sni": "0",
	"psni": "0,00",
	"sa": "1268",
	"psa": "100,00",
	"sna": "0",
	"psna": "0,00",
	"e": "366632",
	"ea": "366632",
	"pea": "100,00",
	"ena": "0",
	"pena": "0,00",
	"esi": "366632",
	"pesi": "100,00",
	"esni": "0",
	"pesni": "0,00",
	"c": "305404",
	"pc": "83,30",
	"a": "61228",
	"pa": "16,70",
	"vscv": "0",
	"vnom": "298369",
	"pvnom": "100,00",
	"vvc": "298369",
	"pvvc": "97,70",
	"vb": "2255",
	"pvb": "0,73",
	"tvn": "4780",
	"ptvn": "1,57",
	"vn": "4780",
	"pvn": "100,00",
	"vnt": "0",
	"pvnt": "0,00",
	"vp": "0",
	"pvp": "0,00",
	"vv": "298369",
	"pvv": "100,00",
	"van": "0",
	"pvan": "0,00",
	"vansj": "0",
	"pvansj": "0,00",
	"tv": "305404",
	"cand": [
		{
			"seq": "1",
			"sqcand": "280001618036",
			"n": "22",
			"nm": "JAIR BOLSONARO",
			"cc": "PL - PP / REPUBLICANOS / PL",
			"nv": "BRAGA NETTO",
			"e": "s",
			"st": "2º turno",
			"dvt": "Válido",
			"vap": "207587",
			"pvap": "69,57"
		},
		{
			"seq": "2",
			"sqcand": "280001607829",
			"n": "13",
			"nm": "LULA",
			"cc": "PT - Federação Brasil da Esperança - FE BRASIL (PT/PC do B/PV) / SOLIDARIEDADE / Federação PSOL REDE (PSOL/REDE) / PSB / AGIR / AVANTE / PROS",
			"nv": "GERALDO ALCKMIN",
			"e": "s",
			"st": "2º turno",
			"dvt": "Válido",
			"vap": "68760",
			"pvap": "23,05"
		},
		{
			"seq": "3",
			"sqcand": "280001607833",
			"n": "15",
			"nm": "SIMONE TEBET",
			"cc": "MDB - MDB / Federação PSDB Cidadania (PSDB/CIDADANIA) / PODE",
			"nv": "MARA GABRILLI",
			"e": "n",
			"st": "Não eleito",
			"dvt": "Válido",
			"vap": "12956",
			"pvap": "4,34"
		},
		{
			"seq": "4",
			"sqcand": "280001612393",
			"n": "12",
			"nm": "CIRO GOMES",
			"cc": "PDT",
			"nv": "ANA PAULA MATOS",
			"e": "n",
			"st": "Não eleito",
			"dvt": "Válido",
			"vap": "6709",
			"pvap": "2,25"
		},
		{
			"seq": "5",
			"sqcand": "280001644128",
			"n": "44",
			"nm": "SORAYA THRONICKE",
			"cc": "UNIÃO",
			"nv": "MARCOS CINTRA",
			"e": "n",
			"st": "Não eleito",
			"dvt": "Válido",
			"vap": "1138",
			"pvap": "0,38"
		},
		{
			"seq": "6",
			"sqcand": "280001603612",
			"n": "30",
			"nm": "FELIPE D&apos;AVILA",
			"cc": "NOVO",
			"nv": "TIAGO MITRAUD",
			"e": "n",
			"st": "Não eleito",
			"dvt": "Válido",
			"vap": "794",
			"pvap": "0,27"
		},
		{
			"seq": "7",
			"sqcand": "280001734029",
			"n": "14",
			"nm": "PADRE KELMON",
			"cc": "PTB",
			"nv": "PASTOR GAMONAL",
			"e": "n",
			"st": "Não eleito",
			"dvt": "Válido",
			"vap": "190",
			"pvap": "0,06"
		},
		{
			"seq": "8",
			"sqcand": "280001607831",
			"n": "16",
			"nm": "VERA",
			"cc": "PSTU",
			"nv": "RAQUEL TREMEMBÉ",
			"e": "n",
			"st": "Não eleito",
			"dvt": "Válido",
			"vap": "75",
			"pvap": "0,03"
		},
		{
			"seq": "9",
			"sqcand": "280001600167",
			"n": "21",
			"nm": "SOFIA MANZANO",
			"cc": "PCB",
			"nv": "ANTONIO ALVES",
			"e": "n",
			"st": "Não eleito",
			"dvt": "Válido",
			"vap": "64",
			"pvap": "0,02"
		},
		{
			"seq": "10",
			"sqcand": "280001602702",
			"n": "80",
			"nm": "LÉO PÉRICLES",
			"cc": "UP",
			"nv": "SAMARA MARTINS",
			"e": "n",
			"st": "Não eleito",
			"dvt": "Válido",
			"vap": "59",
			"pvap": "0,02"
		},
		{
			"seq": "11",
			"sqcand": "280001677435",
			"n": "27",
			"nm": "CONSTITUINTE EYMAEL",
			"cc": "DC",
			"nv": "PROFESSOR BRAVO",
			"e": "n",
			"st": "Não eleito",
			"dvt": "Válido",
			"vap": "37",
			"pvap": "0,01"
		}
	]
}
